build/lib/mfd_model/__init__.py
build/lib/mfd_model/artifacts_manager/__init__.py
build/lib/mfd_model/artifacts_manager/data_structures.py
build/lib/mfd_model/artifacts_manager/models.py
build/lib/mfd_model/config/__init__.py
build/lib/mfd_model/config/__version__.py
build/lib/mfd_model/config/models.py
build/lib/mfd_model/nvm/__init__.py
build/lib/mfd_model/nvm/models.py
mfd_model/__init__.py
mfd_model/artifacts_manager/__init__.py
mfd_model/artifacts_manager/data_structures.py
mfd_model/artifacts_manager/models.py
mfd_model/config/__init__.py
mfd_model/config/__version__.py
mfd_model/config/models.py
mfd_model/nvm/__init__.py
mfd_model/nvm/models.py
mfd_model-0.10.0.dist-info/licenses/AUTHORS.md
mfd_model-0.10.0.dist-info/licenses/LICENSE.md
mfd_model-0.10.0.dist-info/METADATA
mfd_model-0.10.0.dist-info/WHEEL
mfd_model-0.10.0.dist-info/top_level.txt
mfd_model-0.10.0.dist-info/RECORD
