Metadata-Version: 2.4
Name: mfd-model
Version: 0.10.0
Summary: Module for handling models used across multiple MFDs (mostly Pydantic)
Project-URL: Homepage, https://github.com/intel/mfd
Project-URL: Repository, https://github.com/intel/mfd-model
Project-URL: Issues, https://github.com/intel/mfd-model/issues
Project-URL: Changelog, https://github.com/intel/mfd-model/blob/main/CHANGELOG.md
Requires-Python: <3.14,>=3.10
License-File: LICENSE.md
License-File: AUTHORS.md
Requires-Dist: mfd-common-libs<2,>=1.11.0
Provides-Extra: artifacts-manager
Requires-Dist: pydantic<3,>=2.0; extra == "artifacts-manager"
Requires-Dist: mfd-const>=0.23.0; extra == "artifacts-manager"
Provides-Extra: config
Requires-Dist: pydantic<3,>=2.0; extra == "config"
Requires-Dist: mfd-typing>=1.23.0; extra == "config"
Requires-Dist: packaging; extra == "config"
Provides-Extra: nvm
Requires-Dist: pydantic<3,>=2.0; extra == "nvm"
Dynamic: license-file
